tradelink/__init__.py
tradelink/_src/Portfolio.py
tradelink/_src/Requester.py
tradelink/_src/errors/TradeLinkAPIResponseError.py
tradelink/_src/models/ApiResponse.py
tradelink/_src/models/Extended.py
tradelink/_src/models/Portfolio.py
tradelink/_src/models/RequestTypes.py
tradelink/_src/utils/logging.py
python_tradelink-0.1.14.dist-info/METADATA
python_tradelink-0.1.14.dist-info/WHEEL
python_tradelink-0.1.14.dist-info/RECORD
