Metadata-Version: 2.1
Name: python-tradelink
Version: 0.1.14
Summary: TradeLink public API python wrapper
Author: Anton
Author-email: 109826223+Arcadiyyyyyyyy@users.noreply.github.com
Requires-Python: >=3.11,<4.0
Classifier: Programming Language :: Python :: 3
Classifier: Programming Language :: Python :: 3.11
Classifier: Programming Language :: Python :: 3.12
Requires-Dist: aiohttp (>=3.9.1,<4.0.0)
Requires-Dist: pydantic (>=2.5.2,<3.0.0)
